sprite_kit/__init__.py
sprite_kit/agent/__init__.py
sprite_kit/agent/sprite_agent.py
sprite_kit/builder/__init__.py
sprite_kit/builder/sprite_builder.py
sprite_kit/core/__init__.py
sprite_kit/core/color.py
sprite_kit/core/palette.py
sprite_kit/core/rng.py
sprite_kit/core/shape.py
sprite_kit/output/__init__.py
sprite_kit/output/png.py
sprite_kit/output/svg.py
sprite_kit/sprites/__init__.py
sprite_kit/sprites/base.py
sprite_kit/sprites/character.py
sprite_kit/sprites/effect.py
sprite_kit/sprites/icon.py
flexinfer_sprite_kit-0.1.0.dist-info/METADATA
flexinfer_sprite_kit-0.1.0.dist-info/WHEEL
flexinfer_sprite_kit-0.1.0.dist-info/RECORD
