Metadata-Version: 2.4
Name: flexinfer-sprite-kit
Version: 0.1.0
Summary: Procedural sprite generation library with semantic agent API for games
Author-email: Cody Blevins <cody@flexinfer.ai>
License: MIT
Classifier: Operating System :: OS Independent
Classifier: Programming Language :: Python :: 3
Classifier: Programming Language :: Python :: 3.11
Classifier: Programming Language :: Python :: 3.12
Classifier: Topic :: Games/Entertainment
Classifier: Topic :: Multimedia :: Graphics
Requires-Python: >=3.11
Requires-Dist: cairosvg>=2.7.0
Requires-Dist: pillow>=10.0.0
Requires-Dist: pydantic>=2.0.0
Provides-Extra: dev
Requires-Dist: mypy>=1.0.0; extra == 'dev'
Requires-Dist: pre-commit>=3.5.0; extra == 'dev'
Requires-Dist: pytest-cov>=4.0.0; extra == 'dev'
Requires-Dist: pytest>=7.0.0; extra == 'dev'
Requires-Dist: ruff>=0.1.0; extra == 'dev'
